{"cameraMode":{"drawMode":0,"name":"Shaded","section":"Shading Mode"},"sceneLighting":false,"audioPlay":false,"sceneViewState":{"m_AlwaysRefresh":false,"showFog":true,"showSkybox":false,"showFlares":true,"showImageEffects":true,"showParticleSystems":true,"showVisualEffectGraphs":true,"m_FxEnabled":true},"in2DMode":false,"pivot":{"x":-6.518193244934082,"y":-13.255739212036133,"z":33.909706115722659},"rotation":{"x":-0.27856558561325076,"y":0.007776808924973011,"z":-0.002255675382912159,"w":-0.9603832960128784},"size":31.782434463500978,"orthographic":false}